{
	"format_version": "1.8.0",
	"animations": {
		"0": {
			"loop": true,
			"bones": {
				"Pivot": {
					"rotation": {
						"vector": [2.5, 0, 0]
					},
					"position": {
						"vector": [0, -0.5, 0]
					}
				},
				"Body": {
					"rotation": {
						"vector": [-2.49527, -0.21782, 2.5095]
					}
				},
				"Head": {
					"rotation": {
						"vector": [2.7831, 0.64838, 5.02986]
					}
				},
				"LeftEyelid": {
					"position": {
						"vector": [0, 0.25, 0]
					}
				},
				"RightEyelid": {
					"position": {
						"vector": [0, -0.25, 0]
					}
				},
				"LeftEyelidBottom": {
					"position": {
						"vector": [0, -0.35, 0]
					}
				},
				"Jaw": {
					"rotation": {
						"vector": [27.5, 0, 0]
					}
				},
				"LeftArm": {
					"rotation": {
						"vector": [-2.39357, 57.30772, -21.96021]
					}
				},
				"LeftLowerArm": {
					"rotation": {
						"vector": [-31.60659, -7.99365, -12.73415]
					}
				},
				"RightArm": {
					"rotation": {
						"vector": [0, -17.5, 22.5]
					}
				},
				"RightLowerArm": {
					"rotation": {
						"vector": [-32.25489, -5.05904, -5.54401]
					}
				},
				"RightHand": {
					"rotation": {
						"vector": [-15, 0, -2.5]
					}
				},
				"RightLeg": {
					"rotation": {
						"vector": [-7.85783, 19.91082, -1.38134]
					}
				},
				"RightLowerLeg": {
					"rotation": {
						"vector": [15, 0, 0]
					}
				},
				"RightFoot": {
					"rotation": {
						"vector": [-10, 0, 0]
					}
				},
				"LeftLeg": {
					"rotation": {
						"vector": [-7.923, -22.41008, 1.40487]
					}
				},
				"LeftLowerLeg": {
					"rotation": {
						"vector": [12.5, 0, 0]
					}
				},
				"LeftFoot": {
					"rotation": {
						"vector": [-7.5, 0, 0]
					}
				}
			}
		},
		"1": {
			"loop": true,
			"animation_length": 12,
			"bones": {
				"Body": {
					"rotation": {
						"0.0": {
							"vector": [2.5, 0, 0]
						},
						"1.5": {
							"vector": [3, 0, 0]
						},
						"3.0": {
							"vector": [4, 0, 0]
						},
						"4.5": {
							"vector": [-1, 0, 0]
						},
						"6.0": {
							"vector": [2.5, 0, 0]
						},
						"7.5": {
							"vector": [3, 0, 0]
						},
						"9.0": {
							"vector": [4, 0, 0]
						},
						"10.5": {
							"vector": [-1, 0, 0]
						},
						"12.0": {
							"vector": [2.5, 0, 0]
						}
					},
					"position": {
						"0.0": {
							"vector": [0, 0, 0]
						},
						"1.5": {
							"vector": [0, -0.2, 0]
						},
						"3.0": {
							"vector": [0, -0.4, 0]
						},
						"4.5": {
							"vector": [0, 0, 0]
						},
						"6.0": {
							"vector": [0, 0, 0]
						},
						"7.5": {
							"vector": [0, -0.2, 0]
						},
						"9.0": {
							"vector": [0, -0.4, 0]
						},
						"10.5": {
							"vector": [0, 0, 0]
						},
						"12.0": {
							"vector": [0, 0, 0]
						}
					}
				},
				"Head": {
					"rotation": {
						"0.0": {
							"vector": [5, 0, 0]
						},
						"1.5": {
							"vector": [7.33376, -3.34032, -13.03408]
						},
						"3.0": {
							"vector": [5, 0, 0]
						},
						"4.5": {
							"vector": [7.33376, -3.34032, -13.03408]
						},
						"6.0": {
							"vector": [5, 0, 0]
						},
						"7.5": {
							"vector": [7.33376, -3.34032, -13.03408]
						},
						"9.0": {
							"vector": [5, 0, 0]
						},
						"10.5": {
							"vector": [7.33376, -3.34032, -13.03408]
						},
						"12.0": {
							"vector": [5, 0, 0]
						}
					}
				},
				"LeftArm": {
					"rotation": {
						"0.0": {
							"vector": [1.98881, 2.73155, -10.6253]
						},
						"1.5": {
							"vector": [2.21933, 2.54786, -5.62336]
						},
						"3.0": {
							"vector": [2.32833, 2.44866, -3.12295]
						},
						"4.5": {
							"vector": [1.98881, 2.73155, -10.6253]
						},
						"6.0": {
							"vector": [1.98881, 2.73155, -10.6253]
						},
						"7.5": {
							"vector": [2.21933, 2.54786, -5.62336]
						},
						"9.0": {
							"vector": [2.32833, 2.44866, -3.12295]
						},
						"10.5": {
							"vector": [1.98881, 2.73155, -10.6253]
						},
						"12.0": {
							"vector": [1.98881, 2.73155, -10.6253]
						}
					}
				},
				"LeftLowerArm": {
					"rotation": {
						"vector": [-22.5, 0, 0]
					}
				},
				"LeftHand": {
					"rotation": {
						"vector": [0, -12.5, 10]
					}
				},
				"RightArm": {
					"rotation": {
						"0.0": {
							"vector": [1.98881, -2.7316, 10.6253]
						},
						"1.5": {
							"vector": [2.21933, -2.54791, 5.62336]
						},
						"3.0": {
							"vector": [2.32834, -2.44871, 3.12295]
						},
						"4.5": {
							"vector": [1.98881, -2.7316, 10.6253]
						},
						"6.0": {
							"vector": [1.98881, -2.7316, 10.6253]
						},
						"7.5": {
							"vector": [2.21933, -2.54791, 5.62336]
						},
						"9.0": {
							"vector": [2.32834, -2.44871, 3.12295]
						},
						"10.5": {
							"vector": [1.98881, -2.7316, 10.6253]
						},
						"12.0": {
							"vector": [1.98881, -2.7316, 10.6253]
						}
					}
				},
				"RightLowerArm": {
					"rotation": {
						"vector": [-22.5, 0, 0]
					}
				},
				"RightHand": {
					"rotation": {
						"vector": [0.65426, -4.95712, -7.52832]
					}
				},
				"RightLeg": {
					"rotation": {
						"vector": [-12.4833, 4.45906, 0.05936]
					}
				},
				"RightLeg2": {
					"rotation": {
						"vector": [22.5, 0, 0]
					}
				},
				"LeftLeg": {
					"rotation": {
						"vector": [-12.4833, -4.4591, -0.0594]
					}
				},
				"LeftLowerLeg": {
					"rotation": {
						"vector": [22.5, 0, 0]
					}
				},
				"Jaw": {
					"rotation": {
						"0.0": {
							"vector": [-5, 0, 0]
						},
						"1.5": {
							"vector": [7.5, 0, 0]
						},
						"3.0": {
							"vector": [-10, 0, 0]
						},
						"4.5": {
							"vector": [7.5, 0, 0]
						},
						"6.0": {
							"vector": [-5, 0, 0]
						},
						"7.5": {
							"vector": [7.5, 0, 0]
						},
						"9.0": {
							"vector": [-10, 0, 0]
						},
						"10.5": {
							"vector": [-5, 0, 0]
						},
						"12.0": {
							"vector": [-5, 0, 0]
						}
					}
				},
				"RightLowerLeg": {
					"rotation": {
						"vector": [22.5, 0, 0]
					}
				},
				"RightFoot": {
					"rotation": {
						"vector": [-10.00954, 4.99523, -0.21865]
					}
				},
				"LeftFoot": {
					"rotation": {
						"vector": [-10.00954, -4.9952, 0.2187]
					}
				}
			}
		}
	},
	"geckolib_format_version": 2
}